clingmerv-1.12.1.dist-info/DESCRIPTION.rst
clingmerv-1.12.1.dist-info/METADATA
clingmerv-1.12.1.dist-info/RECORD
clingmerv-1.12.1.dist-info/WHEEL
clingmerv-1.12.1.dist-info/entry_points.txt
clingmerv-1.12.1.dist-info/metadata.json
clingmerv-1.12.1.dist-info/top_level.txt
emcli/__init__.py
emcli/__main__.py
emcli/commands/__init__.py
emcli/commands/asg.py
emcli/commands/base.py
emcli/commands/cycle.py
emcli/commands/deploy.py
emcli/commands/instance.py
emcli/commands/patch.py
emcli/commands/publish.py
emcli/commands/service.py
emcli/commands/spinner.py
emcli/commands/toggle.py
emcli/commands/user_confirmation.py
emcli/commands/verify.py
emcli/commands/patching/__init__.py
emcli/commands/patching/patch_file.py
emcli/commands/patching/patch_operation.py
emcli/commands/patching/patch_process.py
emcli/commands/patching/patch_progress.py
emcli/commands/patching/patch_states.py
emcli/commands/patching/patch_table.py
emcli/commands/patching/validate.py
emcli/commands/utils/__init__.py
emcli/commands/utils/asg_health.py
emcli/commands/utils/file_utils.py
